src/__init__.py
src/client/__init__.py
src/client/base.py
src/examples/__init__.py
src/providers/__init__.py
src/providers/base.py
src/providers/facebook.py
src/providers/github.py
src/providers/google.py
src/tests/__init__.py
src/utils/__init__.py
src/utils/error.py
src/utils/request.py
pauth-0.1.0.dist-info/LICENSE
pauth-0.1.0.dist-info/METADATA
pauth-0.1.0.dist-info/WHEEL
pauth-0.1.0.dist-info/top_level.txt
pauth-0.1.0.dist-info/RECORD
